git/__init__.py
git/__version__.py
git/exceptions.py
git/logging.py
git/vendor/git-2.4.3.tar
tests/__init__.py
tests/git_test.py
lambda_git-0.1.1.dist-info/LICENSE
lambda_git-0.1.1.dist-info/METADATA
lambda_git-0.1.1.dist-info/WHEEL
lambda_git-0.1.1.dist-info/top_level.txt
lambda_git-0.1.1.dist-info/RECORD
