Metadata-Version: 2.1
Name: lambda-git
Version: 0.1.1
Summary: A package to install git in AWS Lambda.
Home-page: https://github.com/eredi93/lambda-git
Author: Jacopo Scrinzi
Author-email: scrinzi.jacopo@gmail.com
License: UNKNOWN
Platform: UNKNOWN
Classifier: Programming Language :: Python :: 2
Classifier: Programming Language :: Python :: 2.7
Classifier: Programming Language :: Python :: 3
Classifier: Programming Language :: Python :: 3.6
Classifier: License :: OSI Approved :: MIT License
Classifier: Operating System :: OS Independent
